<keymap version="1" name="Kachko" parent="Mac OS X 10.5+">
  <action id="$LRU">
    <keyboard-shortcut first-keystroke="ctrl q" second-keystroke="r" />
  </action>
  <action id="CloseAllEditorsButActive">
    <keyboard-shortcut first-keystroke="ctrl q" second-keystroke="ctrl w" />
  </action>
  <action id="CloseProject">
    <keyboard-shortcut first-keystroke="ctrl q" second-keystroke="c" />
  </action>
  <action id="Editor LRU">
    <keyboard-shortcut first-keystroke="ctrl q" second-keystroke="r" />
  </action>
  <action id="EditorSelectLine">
    <keyboard-shortcut first-keystroke="ctrl q" second-keystroke="l" />
  </action>
  <action id="EditorToggleColumnMode">
    <keyboard-shortcut first-keystroke="shift meta 8" />
    <keyboard-shortcut first-keystroke="ctrl q" second-keystroke="8" />
  </action>
  <action id="Git.CompareWithBranch">
    <keyboard-shortcut first-keystroke="ctrl q" second-keystroke="ctrl b" />
  </action>
  <action id="Git.ResolveConflicts">
    <keyboard-shortcut first-keystroke="ctrl q" second-keystroke="g" />
  </action>
  <action id="LocalHistory.ShowHistory">
    <keyboard-shortcut first-keystroke="ctrl q" second-keystroke="ctrl h" />
  </action>
  <action id="SplitVertically">
    <keyboard-shortcut first-keystroke="ctrl q" second-keystroke="s" />
  </action>
  <action id="StringManipulation.SwitchStyleAction">
    <keyboard-shortcut first-keystroke="ctrl s" second-keystroke="ctrl s" />
  </action>
  <action id="StringManipulation.ToHyphenCaseAction">
    <keyboard-shortcut first-keystroke="ctrl s" second-keystroke="h" />
  </action>
  <action id="StringManipulation.ToPascalCaseOrCamelCase">
    <keyboard-shortcut first-keystroke="ctrl s" second-keystroke="p" />
  </action>
  <action id="SwitchApply">
    <keyboard-shortcut first-keystroke="ctrl alt enter" />
  </action>
  <action id="SwitchDown">
    <keyboard-shortcut first-keystroke="ctrl alt down" />
  </action>
  <action id="SwitchLeft">
    <keyboard-shortcut first-keystroke="ctrl alt left" />
  </action>
  <action id="SwitchRight">
    <keyboard-shortcut first-keystroke="ctrl alt right" />
  </action>
  <action id="SwitchUp">
    <keyboard-shortcut first-keystroke="ctrl alt up" />
  </action>
  <action id="ToggleInlineHintsAction">
    <keyboard-shortcut first-keystroke="ctrl q" second-keystroke="p" />
  </action>
  <action id="Unsplit">
    <keyboard-shortcut first-keystroke="ctrl q" second-keystroke="u" />
  </action>
  <action id="Vcs.ShowDiffWithLocal">
    <keyboard-shortcut first-keystroke="ctrl q" second-keystroke="d" />
  </action>
  <action id="Vcs.ShowTabbedFileHistory">
    <keyboard-shortcut first-keystroke="ctrl q" second-keystroke="h" />
  </action>
  <action id="osmedile.intellij.stringmanip.EscapeHtmlAction">
    <keyboard-shortcut first-keystroke="ctrl q" second-keystroke="e" />
  </action>
  <action id="osmedile.intellij.stringmanip.ToCamelCaseAction">
    <keyboard-shortcut first-keystroke="ctrl s" second-keystroke="c" />
  </action>
  <action id="osmedile.intellij.stringmanip.UnescapeHtmlAction">
    <keyboard-shortcut first-keystroke="ctrl q" second-keystroke="ctrl e" />
  </action>
  <action id="osmedile.intellij.stringmanip.WordsAndCamelToConstantStyleCaseAction">
    <keyboard-shortcut first-keystroke="ctrl s" second-keystroke="s" />
  </action>
  <action id="osmedile.intellij.stringmanip.WordsCapitalizeAction">
    <keyboard-shortcut first-keystroke="ctrl s" second-keystroke="up" />
  </action>
</keymap>